fuckexcel/FuckExcel.py
fuckexcel/__dependencies__.py
fuckexcel/__init__.py
fuckexcel-0.0.3.dist-info/LICENSE
fuckexcel-0.0.3.dist-info/METADATA
fuckexcel-0.0.3.dist-info/WHEEL
fuckexcel-0.0.3.dist-info/RECORD
