Metadata-Version: 2.1
Name: fuckexcel
Version: 0.0.3
Summary: Using Excel as 2D Array
License: MIT
Author: Rhythmicc
Author-email: rhythmlian.cn@gmail.com
Requires-Python: >=3.11,<4.0
Classifier: License :: OSI Approved :: MIT License
Classifier: Programming Language :: Python :: 3
Classifier: Programming Language :: Python :: 3.11
Classifier: Programming Language :: Python :: 3.12
Requires-Dist: openpyxl (>=3.1.5,<4.0.0)
